README.md
setup.py
matmos/__init__.py
matmos/atmosphere.py
matmos/constants.py
matmos.egg-info/PKG-INFO
matmos.egg-info/SOURCES.txt
matmos.egg-info/dependency_links.txt
matmos.egg-info/requires.txt
matmos.egg-info/top_level.txt
matmos/models/ISA.py
matmos/models/__init__.py
tests/__init__.py
tests/test_matmos.py