Metadata-Version: 2.1
Name: matmos
Version: 0.0.0a3
Summary: Library of atmospheric models
Home-page: https://github.com/antonlopezr/matmos
Author: Antonio Lopez Rivera
Author-email: antonlopezr99@gmail.com
License: UNKNOWN
Platform: UNKNOWN
Classifier: Programming Language :: Python :: 3
Classifier: License :: OSI Approved :: GNU General Public License v3 (GPLv3)
Classifier: Operating System :: OS Independent
Requires-Python: >=3.6
